github_mcp_server.py
github_mcp_server_unofficial-0.12.1.data/scripts/github-mcp-server
github_mcp_server_unofficial-0.12.1.dist-info/METADATA
github_mcp_server_unofficial-0.12.1.dist-info/WHEEL
github_mcp_server_unofficial-0.12.1.dist-info/licenses/LICENSE
github_mcp_server_unofficial-0.12.1.dist-info/RECORD
